README.md
setup.cfg
setup.py
EnjoyDevAPI/__init__.py
EnjoyDevAPI/api.py
EnjoyDevAPI/errors.py
EnjoyDevAPI/models.py
EnjoyDevAPI.egg-info/PKG-INFO
EnjoyDevAPI.egg-info/SOURCES.txt
EnjoyDevAPI.egg-info/dependency_links.txt
EnjoyDevAPI.egg-info/not-zip-safe
EnjoyDevAPI.egg-info/top_level.txt