Metadata-Version: 1.0
Name: EnjoyDevAPI
Version: 2.2
Summary: BY RTC API
Home-page: UNKNOWN
Author: UNKNOWN
Author-email: rrrrd97mailru@gmail.com
License: UNKNOWN
Platform: UNKNOWN
